[
  {
    "id": "01",
    "filename": "一 Ichi: 01",
    "title": "一 Ichi",
    "dimensions": "300×400 mm",
    "material": "Wooden panel",
    "paper": "Japanese paper Torinoko Gampi"
  },
  {
    "id": "02",
    "filename": "二 Ni: 02",
    "title": "二 Ni",
    "dimensions": "300×400 mm",
    "material": "Wooden panel",
    "paper": "Japanese paper Torinoko Gampi"
  },
  {
    "id": "03",
    "filename": "三 San: 03",
    "title": "三 San",
    "dimensions": "300×400 mm",
    "material": "Wooden panel",
    "paper": "Japanese paper Torinoko Gampi"
  },
  {
    "id": "04",
    "filename": "四 Yon: 04",
    "title": "四 Yon",
    "dimensions": "300×420 mm",
    "material": "Wooden panel",
    "paper": "Japanese paper Kumohada Mashi"
  },
  {
    "id": "05",
    "filename": "五　Go: 05",
    "title": "五 Go",
    "dimensions": "300×420 mm",
    "material": "Wooden panel",
    "paper": "Japanese paper Shiromashi"
  },
  {
    "id": "06",
    "filename": "六 Roku: 06",
    "title": "六 Roku",
    "dimensions": "300×400 mm",
    "material": "Wooden panel",
    "paper": "Japanese paper Kumohada Mashi"
  },
  {
    "id": "07",
    "filename": "七 Shichi: 07",
    "title": "七 Shichi",
    "dimensions": "300×400 mm",
    "material": "Wooden panel",
    "paper": "Japanese paper Torinoko Gampi"
  },
  {
    "id": "08",
    "filename": "八 Hachi: 08",
    "title": "八 Hachi",
    "dimensions": "300×420 mm",
    "material": "Wooden panel",
    "paper": "Japanese paper Kumohada Mashi"
  },
  {
    "id": "09",
    "filename": "九 Kyū: 09",
    "title": "九 Kyū",
    "dimensions": "300×400 mm",
    "material": "Wooden panel",
    "paper": "Japanese paper Torinoko Gampi"
  },
  {
    "id": "10",
    "filename": "十 Jū: 10",
    "title": "十 Jū",
    "dimensions": "300×400 mm",
    "material": "Wooden panel",
    "paper": "Japanese paper Kumohada Mashi"
  },
  {
    "id": "11",
    "filename": "十一　Jū ichi: 11",
    "title": "十一 Jū ichi",
    "dimensions": "300×400 mm",
    "material": "Wooden panel",
    "paper": "Japanese paper Kumohada Mashi"
  },
  {
    "id": "12",
    "filename": "十二　 Jū ni: 12",
    "title": "十二 Jū ni",
    "dimensions": "300×420 mm",
    "material": "Wooden panel",
    "paper": "Japanese paper Torinoko Gampi"
  },
  {
    "id": "13",
    "filename": "十三　Jū san: 13",
    "title": "十三 Jū san",
    "dimensions": "500×200 mm",
    "material": "Wooden panel",
    "paper": "Japanese paper Mitsumata Torinoko"
  },
  {
    "id": "14",
    "filename": "十四　 Jū  yon: 14",
    "title": "十四 Jū yon",
    "dimensions": "500×200 mm",
    "material": "Wooden panel",
    "paper": "Japanese paper Mitsumata Torinoko"
  },
  {
    "id": "15",
    "filename": "十五　Jū go: 15",
    "title": "十五 Jū go",
    "dimensions": "500×200 mm",
    "material": "Wooden panel",
    "paper": "Japanese paper Mitsumata Torinoko"
  },
  {
    "id": "16",
    "filename": "十六 Jū roku: 16",
    "title": "十六 Jū roku",
    "dimensions": "600×870 mm",
    "material": "Wooden panel",
    "paper": "Japanese paper Shiromashi"
  },
  {
    "id": "17",
    "filename": "十七 Jū Shichi: 17",
    "title": "十七 Jū Shichi",
    "dimensions": "630×930 mm",
    "material": "Wooden panel",
    "paper": "Japanese paper Tosa Washi"
  },
  {
    "id": "18",
    "filename": "十八 Jū Hachi: 18",
    "title": "十八 Jū Hachi",
    "dimensions": "600×870 mm",
    "material": "Wooden panel",
    "paper": "Japanese paper Shiromashi"
  },
  {
    "id": "19",
    "filename": "十九 Jū Kyu: 19",
    "title": "十九 Jū Kyu",
    "dimensions": "600×870 mm",
    "material": "Wooden panel",
    "paper": "Japanese paper Kumohada Mashi"
  }
]
